{
	"version": "1.1.9",
	"app_name": "fman",
	"main_module": "src/main/python/fman/main.py",
	"freeze_dir": "target/${app_name}",
	"test_dirs": [
		"src/unittest/python",
		"src/main/resources/base/Plugins/Core",
		"src/integrationtest/python"
	],
	"mac_bundle_identifier": "io.fman.fman",
	"arch_pkg": "target/fman.pkg.tar.xz",
	"release": false,
	"environment": "local",
	"server_url": "http://127.0.0.1:8000",
	"appcast_url": "${server_url}/updates/Appcast.xml",
	"record_release_url": "${server_url}/api/record-release/",
	"server_api_secret": "k92XhhhmOf8rD7QJ",
	"info_plist_extra": "<key>NSAppTransportSecurity</key>\n\t<dict>\n\t\t<key>NSAllowsArbitraryLoads</key>\n\t\t<true/>\n\t</dict>",
	"local_media_dir": "../fman.io/media",
	"server_media_dir": "/home/fman/src/media",
	"server_user": "fman@fman.io",
	"ssh_key": "conf/ssh/id_rsa",
	"resources_to_filter": [
		"src/main/resources/base/constants.json",
		"src/main/resources/mac-frozen/Contents/Info.plist",
		"src/main/resources/mac-frozen/Contents/SharedSupport/bin/fman"
	],
	"gpg_key": "B015FE599CFAF7EB",
	"gpg_pass": "fenst4r",
	"aws_access_key_id": "AKIAIWTB3R6KKMMTWXEA",
	"aws_secret_access_key": "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",
	"aws_bucket": "fman",
	"aws_distribution_id": "E36JGR8Q7NMYHR"
}